trp/__init__.py
trp/cli.py
trp/scraper.py
trp/testing.py
trp/viewer.py
trp-0.1.6a1.dist-info/DESCRIPTION.rst
trp-0.1.6a1.dist-info/METADATA
trp-0.1.6a1.dist-info/RECORD
trp-0.1.6a1.dist-info/WHEEL
trp-0.1.6a1.dist-info/entry_points.txt
trp-0.1.6a1.dist-info/metadata.json
trp-0.1.6a1.dist-info/top_level.txt
