Metadata-Version: 1.1
Name: trp
Version: 0.1.6a1
Summary: Third-party Regis Python Module
Home-page: https://github.com/Apexal/trp
Author: Frank Matranga
Author-email: thefrankmatranga@gmail.com
License: MIT
Keywords: regis moodle scraper education school academics
Platform: UNKNOWN
Classifier: Development Status :: 3 - Alpha
Classifier: Intended Audience :: Developers
Classifier: License :: OSI Approved :: MIT License
Classifier: Programming Language :: Python :: 2
